vpt_core/__init__.py
vpt_core/image/__init__.py
vpt_core/image/filter.py
vpt_core/image/filter_factory.py
vpt_core/io/__init__.py
vpt_core/io/image.py
vpt_core/io/input_tools.py
vpt_core/io/output_tools.py
vpt_core/io/regex_tools.py
vpt_core/io/vzgfs.py
vpt_core/log.py
vpt_core/segmentation/__init__.py
vpt_core/segmentation/fuse.py
vpt_core/segmentation/geometry_utils.py
vpt_core/segmentation/polygon_utils.py
vpt_core/segmentation/seg_result.py
vpt_core/segmentation/segmentation_base.py
vpt_core/segmentation/segmentation_item.py
vpt_core/segmentation/segmentation_task.py
vpt_core/segmentation/task_input_data.py
vpt_core/utils/__init__.py
vpt_core/utils/base_case.py
vpt_core/utils/copy_utils.py
vpt_core/utils/segmentation_utils.py
vpt_core-1.2.0.dist-info/LICENSE.md
vpt_core-1.2.0.dist-info/METADATA
vpt_core-1.2.0.dist-info/WHEEL
vpt_core-1.2.0.dist-info/RECORD
