Metadata-Version: 2.1
Name: vpt_core
Version: 1.2.0
Summary: Core components for the Vizgen Post-processing Tool
Home-page: https://github.com/Vizgen/vpt-core
License: Apache-2.0
Author: Vizgen
Author-email: techsupport@vizgen.com
Maintainer: Timothy Wiggin
Maintainer-email: timothy.wiggin@vizgen.com
Requires-Python: >=3.9,<3.11
Classifier: Development Status :: 5 - Production/Stable
Classifier: License :: OSI Approved :: Apache Software License
Classifier: Natural Language :: English
Classifier: Operating System :: MacOS :: MacOS X
Classifier: Operating System :: Microsoft :: Windows
Classifier: Operating System :: POSIX :: Linux
Classifier: Programming Language :: Python :: 3
Classifier: Programming Language :: Python :: 3.9
Classifier: Programming Language :: Python :: 3.10
Classifier: Topic :: Scientific/Engineering :: Bio-Informatics
Classifier: Topic :: Scientific/Engineering :: Image Processing
Requires-Dist: boto3 (>=1.17)
Requires-Dist: fsspec (>=2021.10.0)
Requires-Dist: gcsfs (>=2021.10.0)
Requires-Dist: geopandas (>=0.13.2)
Requires-Dist: numpy (>=1.24.3,<2.0.0)
Requires-Dist: opencv-python-headless (>=4.6.0.66)
Requires-Dist: pandas (>=2.0.3,<3.0.0)
Requires-Dist: psutil
Requires-Dist: pyarrow (>=8.0.0,<14.0.0)
Requires-Dist: python-dotenv (>=0.20.0)
Requires-Dist: rasterio (>=1.3.0,<1.3.6)
Requires-Dist: s3fs (>=2021.10.0)
Requires-Dist: scikit-image (>=0.19.3)
Requires-Dist: shapely (>=2.0.0)
Requires-Dist: tenacity (>=8.2.2)
Requires-Dist: tqdm
Project-URL: Documentation, https://vizgen.github.io/vizgen-postprocessing/
Project-URL: Repository, https://github.com/Vizgen/vpt-core
